Metadata-Version: 2.1
Name: odoo13-addon-crm-project
Version: 13.0.1.1.0
Summary: Create Tasks from Leads/Opportunities
Home-page: https://github.com/OCA/crm
Author: Odoo S.A., Odoo Community Association (OCA), Tecnativa
Author-email: support@odoo-community.org
License: LGPL-3
Platform: UNKNOWN
Classifier: Programming Language :: Python
Classifier: Framework :: Odoo
Classifier: Framework :: Odoo :: 13.0
Classifier: License :: OSI Approved :: GNU Lesser General Public License v3 (LGPLv3)
Requires-Python: >=3.5
Requires-Dist: odoo (<13.1dev,>=13.0a)
